inflexion/__init__.py
inflexion/lexicon.py
inflexion/main.py
inflexion/sandhi.py
inflexion/stemming.py
inflexion-0.8.0.dist-info/DESCRIPTION.rst
inflexion-0.8.0.dist-info/METADATA
inflexion-0.8.0.dist-info/RECORD
inflexion-0.8.0.dist-info/WHEEL
inflexion-0.8.0.dist-info/metadata.json
inflexion-0.8.0.dist-info/top_level.txt
