Metadata-Version: 2.0
Name: inflexion
Version: 0.8.0
Summary: generic code for morphological analysis
Home-page: http://github.com/jtauber/inflexion
Author: James Tauber
Author-email: jtauber@jtauber.com
License: MIT
Platform: UNKNOWN
Classifier: Development Status :: 4 - Beta
Classifier: License :: OSI Approved :: MIT License
Classifier: Programming Language :: Python :: 3.3
Classifier: Programming Language :: Python :: 3.4
Classifier: Programming Language :: Python :: 3.5
Classifier: Topic :: Text Processing
Classifier: Topic :: Text Processing :: Linguistic
